state_service_utils/__init__.py
state_service_utils/conf.py
state_service_utils/enums_client.py
state_service_utils/exceptions.py
state_service_utils/logging.py
state_service_utils/utils.py
state_service_utils/datafiles/enums_template.json
vtb_state_service_utils-1.8.1.dist-info/METADATA
vtb_state_service_utils-1.8.1.dist-info/WHEEL
vtb_state_service_utils-1.8.1.dist-info/top_level.txt
vtb_state_service_utils-1.8.1.dist-info/RECORD
