Metadata-Version: 2.1
Name: vtb-state-service-utils
Version: 1.8.1
Summary: utils for VTB state service
Home-page: https://bitbucket.org/Michail_Shutov/state_service_utils
Author: Mikhail Shutov
Author-email: michael-russ@yandex.ru
Requires-Dist: aiohttp (>=3.6.2)
Requires-Dist: aio-pika (>=6.6.1)
Requires-Dist: simplejson (>=3.17.2)
Requires-Dist: requests (>=2.18.0)
Requires-Dist: ujson (>=2.0.2)
Requires-Dist: envparse (>=0.2.0)
Requires-Dist: vtb-py-logging (>=1.1.11)
Requires-Dist: vtb-http-interaction (>=0.1.7)
Requires-Dist: asgiref (>=3.5.0)
Requires-Dist: vtb-cloud-sdk (==1.13)
Provides-Extra: test
Requires-Dist: pytest ; extra == 'test'
Requires-Dist: pytest-env ; extra == 'test'
Requires-Dist: pytest-dotenv ; extra == 'test'
Requires-Dist: pytest-mock ; extra == 'test'
Requires-Dist: pylint ; extra == 'test'
Requires-Dist: pytest-asyncio ; extra == 'test'
Requires-Dist: python-dotenv ; extra == 'test'
Requires-Dist: mq-misc ; extra == 'test'
